setup.cfg
setup.py
LazyScripts/LazyCSV.py
LazyScripts/LazyJSON.py
LazyScripts/LazyMultithread.py
LazyScripts/LazySoup.py
LazyScripts/LazyTor.py
LazyScripts/__init__.py
LazyScripts/version.py
LazyScripts.egg-info/PKG-INFO
LazyScripts.egg-info/SOURCES.txt
LazyScripts.egg-info/dependency_links.txt
LazyScripts.egg-info/requires.txt
LazyScripts.egg-info/top_level.txt