Metadata-Version: 1.1
Name: LazyScripts
Version: 0.3.0
Summary: Useful python modules for lazy scripting.
Home-page: https://github.com/jameswenzel/LazyScripts
Author: James Wenzel
Author-email: wenzel.james.r@gmail.com
License: Apache License, Version 2.0
Download-URL: https://github.com/jameswenzel/LazyScripts/tarball/0.3.0
Keywords: lazy,csv,tor,multithread,beautifulsoup,json
Platform: UNKNOWN
